{"commitInfo":{"timestamp":1753529092162,"operation":"WRITE","operationParameters":{"mode":"Overwrite","partitionBy":"[]"},"isolationLevel":"Serializable","isBlindAppend":false,"operationMetrics":{"numFiles":"1","numRemovedFiles":"0","numRemovedBytes":"0","numOutputRows":"5","numOutputBytes":"3085"},"engineInfo":"Apache-Spark/4.0.0 Delta-Lake/4.0.0","txnId":"cf2c914b-e812-4aa0-b259-9753346b3903"}}
{"metaData":{"id":"14e05933-a675-49ae-b419-3c826c7180ec","format":{"provider":"parquet","options":{}},"schemaString":"{\"type\":\"struct\",\"fields\":[{\"name\":\"ReturnID\",\"type\":\"string\",\"nullable\":true,\"metadata\":{}},{\"name\":\"OrderID\",\"type\":\"string\",\"nullable\":true,\"metadata\":{}},{\"name\":\"ProductID\",\"type\":\"string\",\"nullable\":true,\"metadata\":{}},{\"name\":\"CustomerID\",\"type\":\"string\",\"nullable\":true,\"metadata\":{}},{\"name\":\"ReturnDate\",\"type\":\"date\",\"nullable\":true,\"metadata\":{}},{\"name\":\"RefundAmount\",\"type\":\"double\",\"nullable\":true,\"metadata\":{}},{\"name\":\"Reason\",\"type\":\"string\",\"nullable\":true,\"metadata\":{}},{\"name\":\"ingestion_time\",\"type\":\"timestamp\",\"nullable\":true,\"metadata\":{}},{\"name\":\"source\",\"type\":\"string\",\"nullable\":true,\"metadata\":{}}]}","partitionColumns":[],"configuration":{},"createdTime":1753529091782}}
{"protocol":{"minReaderVersion":1,"minWriterVersion":2}}
{"add":{"path":"part-00000-7294cded-4c1f-41b3-9561-f4d826c0e925-c000.snappy.parquet","partitionValues":{},"size":3085,"modificationTime":1753529092041,"dataChange":true,"stats":"{\"numRecords\":5,\"minValues\":{\"ReturnID\":\"R5001\",\"OrderID\":\"O1002\",\"ProductID\":\"P003\",\"CustomerID\":\"C001\",\"ReturnDate\":\"2024-01-10\",\"RefundAmount\":9.99,\"Reason\":\"Did Not Work\",\"ingestion_time\":\"2025-07-26T16:54:51.831+05:30\",\"source\":\"returnsRefunds.csv\"},\"maxValues\":{\"ReturnID\":\"R5005\",\"OrderID\":\"O1014\",\"ProductID\":\"P007\",\"CustomerID\":\"C005\",\"ReturnDate\":\"2024-01-21\",\"RefundAmount\":18.25,\"Reason\":\"Wrong Item\",\"ingestion_time\":\"2025-07-26T16:54:51.831+05:30\",\"source\":\"returnsRefunds.csv\"},\"nullCount\":{\"ReturnID\":0,\"OrderID\":0,\"ProductID\":0,\"CustomerID\":0,\"ReturnDate\":0,\"RefundAmount\":0,\"Reason\":0,\"ingestion_time\":0,\"source\":0}}"}}
