{"commitInfo":{"timestamp":1753529116683,"operation":"WRITE","operationParameters":{"mode":"Overwrite","partitionBy":"[]"},"isolationLevel":"Serializable","isBlindAppend":false,"operationMetrics":{"numFiles":"1","numRemovedFiles":"0","numRemovedBytes":"0","numOutputRows":"16","numOutputBytes":"3538"},"engineInfo":"Apache-Spark/4.0.0 Delta-Lake/4.0.0","txnId":"17d78d58-6d4a-4aa7-a45b-81856e7be1e4"}}
{"metaData":{"id":"cdffba0a-69a8-483f-b643-6ae5d3653238","format":{"provider":"parquet","options":{}},"schemaString":"{\"type\":\"struct\",\"fields\":[{\"name\":\"CustomerID\",\"type\":\"string\",\"nullable\":true,\"metadata\":{}},{\"name\":\"OrderID\",\"type\":\"string\",\"nullable\":true,\"metadata\":{}},{\"name\":\"ProductID\",\"type\":\"string\",\"nullable\":true,\"metadata\":{}},{\"name\":\"link-order-customer-product_HK\",\"type\":\"string\",\"nullable\":true,\"metadata\":{}},{\"name\":\"load_date\",\"type\":\"timestamp\",\"nullable\":true,\"metadata\":{}},{\"name\":\"source\",\"type\":\"string\",\"nullable\":true,\"metadata\":{}}]}","partitionColumns":[],"configuration":{},"createdTime":1753529115564}}
{"protocol":{"minReaderVersion":1,"minWriterVersion":2}}
{"add":{"path":"part-00000-4cb433b4-064e-4839-b257-f9f6ce42c27d-c000.snappy.parquet","partitionValues":{},"size":3538,"modificationTime":1753529116551,"dataChange":true,"stats":"{\"numRecords\":16,\"minValues\":{\"CustomerID\":\"C001\",\"OrderID\":\"O1001\",\"ProductID\":\"P001\",\"link-order-customer-product_HK\":\"0c824cd0d2a62737dc8c2398e75b03d7\",\"load_date\":\"2025-07-26T16:55:15.604+05:30\",\"source\":\"salesOrder\"},\"maxValues\":{\"CustomerID\":\"C011\",\"OrderID\":\"O1016\",\"ProductID\":\"P008\",\"link-order-customer-product_HK\":\"fd30f3bb9e61a19ad4472a8b7f814b63\",\"load_date\":\"2025-07-26T16:55:15.604+05:30\",\"source\":\"salesOrder\"},\"nullCount\":{\"CustomerID\":0,\"OrderID\":0,\"ProductID\":0,\"link-order-customer-product_HK\":0,\"load_date\":0,\"source\":0}}"}}
